awslabs/__init__.py
awslabs/openapi_mcp_server/__init__.py
awslabs/openapi_mcp_server/server.py
awslabs/openapi_mcp_server/api/__init__.py
awslabs/openapi_mcp_server/api/config.py
awslabs/openapi_mcp_server/auth/__init__.py
awslabs/openapi_mcp_server/auth/api_key_auth.py
awslabs/openapi_mcp_server/auth/auth_cache.py
awslabs/openapi_mcp_server/auth/auth_errors.py
awslabs/openapi_mcp_server/auth/auth_factory.py
awslabs/openapi_mcp_server/auth/auth_protocol.py
awslabs/openapi_mcp_server/auth/auth_provider.py
awslabs/openapi_mcp_server/auth/base_auth.py
awslabs/openapi_mcp_server/auth/basic_auth.py
awslabs/openapi_mcp_server/auth/bearer_auth.py
awslabs/openapi_mcp_server/auth/cognito_auth.py
awslabs/openapi_mcp_server/auth/register.py
awslabs/openapi_mcp_server/patch/__init__.py
awslabs/openapi_mcp_server/prompts/__init__.py
awslabs/openapi_mcp_server/prompts/models.py
awslabs/openapi_mcp_server/prompts/prompt_manager.py
awslabs/openapi_mcp_server/prompts/generators/__init__.py
awslabs/openapi_mcp_server/prompts/generators/operation_prompts.py
awslabs/openapi_mcp_server/prompts/generators/workflow_prompts.py
awslabs/openapi_mcp_server/utils/__init__.py
awslabs/openapi_mcp_server/utils/cache_provider.py
awslabs/openapi_mcp_server/utils/config.py
awslabs/openapi_mcp_server/utils/error_handler.py
awslabs/openapi_mcp_server/utils/http_client.py
awslabs/openapi_mcp_server/utils/metrics_provider.py
awslabs/openapi_mcp_server/utils/openapi.py
awslabs/openapi_mcp_server/utils/openapi_validator.py
awslabs_openapi_mcp_server-0.2.12.dist-info/METADATA
awslabs_openapi_mcp_server-0.2.12.dist-info/WHEEL
awslabs_openapi_mcp_server-0.2.12.dist-info/entry_points.txt
awslabs_openapi_mcp_server-0.2.12.dist-info/licenses/LICENSE
awslabs_openapi_mcp_server-0.2.12.dist-info/licenses/NOTICE
awslabs_openapi_mcp_server-0.2.12.dist-info/RECORD
