Metadata-Version: 2.4
Name: awslabs.openapi-mcp-server
Version: 0.2.12
Summary: An AWS Labs Model Context Protocol (MCP) server for OpenAPI
Project-URL: Homepage, https://awslabs.github.io/mcp/
Project-URL: Documentation, https://awslabs.github.io/mcp/servers/openapi-mcp-server/
Project-URL: Source, https://github.com/awslabs/mcp.git
Project-URL: Bug Tracker, https://github.com/awslabs/mcp/issues
Project-URL: Changelog, https://github.com/awslabs/mcp/blob/main/src/openapi-mcp-server/CHANGELOG.md
Author: Amazon Web Services
Author-email: "AWSLabs Model Context Protocol (MCP)" <203918161+awslabs-mcp@users.noreply.github.com>
License: Apache-2.0
License-File: LICENSE
License-File: NOTICE
Classifier: License :: OSI Approved :: Apache Software License
Classifier: Operating System :: OS Independent
Classifier: Programming Language :: Python
Classifier: Programming Language :: Python :: 3
Classifier: Programming Language :: Python :: 3.10
Classifier: Programming Language :: Python :: 3.11
Classifier: Programming Language :: Python :: 3.12
Classifier: Programming Language :: Python :: 3.13
Requires-Python: >=3.10
Requires-Dist: bcrypt>=4.3.0
Requires-Dist: boto3>=1.39.3
Requires-Dist: cachetools>=6.1.0
Requires-Dist: fastmcp>=2.14.0
Requires-Dist: httpx>=0.28.1
Requires-Dist: loguru>=0.7.3
Requires-Dist: openapi-spec-validator>=0.7.2
Requires-Dist: prance>=25.4.8.0
Requires-Dist: pydantic>=2.11.7
Requires-Dist: pyyaml>=6.0.2
Requires-Dist: tenacity>=9.1.2
Requires-Dist: typing-extensions>=4.14.1
Requires-Dist: uvicorn>=0.35.0
Provides-Extra: all
Requires-Dist: prometheus-client>=0.17.0; extra == 'all'
Requires-Dist: pyyaml>=6.0.0; extra == 'all'
Provides-Extra: dev
Requires-Dist: commitizen>=4.8.3; extra == 'dev'
Requires-Dist: lxml>=6.0.0; extra == 'dev'
Requires-Dist: pre-commit>=4.2.0; extra == 'dev'
Requires-Dist: pyright>=1.1.402; extra == 'dev'
Requires-Dist: pytest-asyncio>=1.0.0; extra == 'dev'
Requires-Dist: pytest-cov>=6.2.1; extra == 'dev'
Requires-Dist: pytest>=8.4.1; extra == 'dev'
Requires-Dist: ruff>=0.12.2; extra == 'dev'
Provides-Extra: prometheus
Requires-Dist: prometheus-client>=0.22.1; extra == 'prometheus'
Provides-Extra: test
Requires-Dist: pytest-asyncio>=1.0.0; extra == 'test'
Requires-Dist: pytest-cov>=6.2.1; extra == 'test'
Requires-Dist: pytest-mock>=3.14.1; extra == 'test'
Requires-Dist: pytest>=8.4.1; extra == 'test'
Provides-Extra: yaml
Requires-Dist: pyyaml>=6.0.2; extra == 'yaml'
